roar_net_api/__init__.py
roar_net_api/py.typed
roar_net_api/algorithms/__init__.py
roar_net_api/algorithms/beam_search.py
roar_net_api/algorithms/best_improvement.py
roar_net_api/algorithms/first_improvement.py
roar_net_api/algorithms/grasp.py
roar_net_api/algorithms/greedy_construction.py
roar_net_api/algorithms/rls.py
roar_net_api/algorithms/sa.py
roar_net_api/operations/__init__.py
roar_net_api/operations/apply_move.py
roar_net_api/operations/construction_neighbourhood.py
roar_net_api/operations/copy_solution.py
roar_net_api/operations/destruction_neighbourhood.py
roar_net_api/operations/empty_solution.py
roar_net_api/operations/heuristic_solution.py
roar_net_api/operations/invert_move.py
roar_net_api/operations/local_neighbourhood.py
roar_net_api/operations/lower_bound.py
roar_net_api/operations/lower_bound_increment.py
roar_net_api/operations/moves.py
roar_net_api/operations/objective_value.py
roar_net_api/operations/objective_value_increment.py
roar_net_api/operations/random_move.py
roar_net_api/operations/random_moves_without_replacement.py
roar_net_api/operations/random_solution.py
roar_net_api/types/__init__.py
roar_net_api/types/move.py
roar_net_api/types/neighbourhood.py
roar_net_api/types/problem.py
roar_net_api/types/solution.py
roar_net_api-0.1.0.dist-info/METADATA
roar_net_api-0.1.0.dist-info/WHEEL
roar_net_api-0.1.0.dist-info/licenses/LICENSES/Apache-2.0.txt
roar_net_api-0.1.0.dist-info/licenses/LICENSES/CC-BY-4.0.txt
roar_net_api-0.1.0.dist-info/licenses/LICENSES/CC0-1.0.txt
roar_net_api-0.1.0.dist-info/RECORD
