Metadata-Version: 2.4
Name: roar-net-api
Version: 0.1.0
Summary: Python implementation of the ROAR-NET API Specification
Project-URL: Repository, https://github.com/roar-net/roar-net-api-py
Project-URL: Issues, https://github.com/roar-net/roar-net-api-py/issues
Maintainer-email: Alexandre Jesus <me@adbjesus.com>, "Carlos M. Fonseca" <cmfonsec@dei.uc.pt>
License-Expression: Apache-2.0 AND CC-BY-4.0
License-File: LICENSES/Apache-2.0.txt
License-File: LICENSES/CC-BY-4.0.txt
License-File: LICENSES/CC0-1.0.txt
Classifier: Development Status :: 3 - Alpha
Classifier: Intended Audience :: Developers
Classifier: Intended Audience :: Science/Research
Classifier: License :: OSI Approved :: Apache Software License
Classifier: Operating System :: OS Independent
Classifier: Programming Language :: Python
Classifier: Programming Language :: Python :: 3
Classifier: Programming Language :: Python :: 3 :: Only
Classifier: Programming Language :: Python :: 3.11
Classifier: Programming Language :: Python :: 3.12
Classifier: Programming Language :: Python :: 3.13
Classifier: Programming Language :: Python :: Implementation :: CPython
Classifier: Programming Language :: Python :: Implementation :: PyPy
Classifier: Topic :: Scientific/Engineering
Classifier: Topic :: Software Development
Classifier: Typing :: Typed
Requires-Python: >=3.11
